mds_mdsbackuplib-0.5.5.dist-info/DESCRIPTION.rst
mds_mdsbackuplib-0.5.5.dist-info/METADATA
mds_mdsbackuplib-0.5.5.dist-info/RECORD
mds_mdsbackuplib-0.5.5.dist-info/WHEEL
mds_mdsbackuplib-0.5.5.dist-info/metadata.json
mds_mdsbackuplib-0.5.5.dist-info/top_level.txt
mdsbackuplib/__init__.py
mdsbackuplib/backuplib.py
mdsbackuplib/runexample.py
